<object name="semi di mela">
  <description>
    <command>text "Ti rendi conto delle cose assurde che mi fai raccogliere, sì?"</command>
  </description>
  <inventory />
  <location name="studio">
    <hotspot ID="pianta carnivora">
      <command>text "Ehi bella, guarda cos'ho qui per te."</command>
      <command>animation -skinny 00 -o=400,5 -a "skinny_semi"</command>
      <command>wait 0,7</command>
      <command>sound "pianta_carnivora_muore"</command>
      <command>animation -"me" 00 -o=60,233 "pianta_carnivora_muore"</command>
      <command>bitmap -"me" "pianta_carnivora_morta"</command>
      <command>internal -"me" -g 1</command>
      <command>viewer -"me" (437,764)</command>
      <command>hide +"medaglione_geralt"</command>
      <command>show +"medaglione_geralt_fermo"</command>
      <command>throw "semi_mela"</command>
      <command>internal -"ritratto" 1</command>
    </hotspot>
  </location>
  <location name="spiaggia">
    <hotspot ID="calderone_presente">
      <command>pose d</command>
      <command>text "Ormai me li hai fatti raccogliere e non ho intenzione di tornare sui miei passi." $165</command>
    </hotspot>
    <hotspot ID="calderone_1861">
      <command>pose d</command>
      <command>text "Ormai me li hai fatti raccogliere e non ho intenzione di tornare sui miei passi." $165</command>
    </hotspot>
    <hotspot ID="calderone_1981">
      <command>pose d</command>
      <command>text "Ormai me li hai fatti raccogliere e non ho intenzione di tornare sui miei passi." $165</command>
    </hotspot>
  </location>
</object>